webscraper/__init__.py
webscraper/scraper.py
webscraper/utils.py
ariwebscraper-1.0.0.dist-info/LICENSE
ariwebscraper-1.0.0.dist-info/METADATA
ariwebscraper-1.0.0.dist-info/WHEEL
ariwebscraper-1.0.0.dist-info/top_level.txt
ariwebscraper-1.0.0.dist-info/RECORD
