Metadata-Version: 2.2
Name: ariwebscraper
Version: 1.0.0
Summary: A simple web scraper
Home-page: https://github.com/ilkeryolundagerek/ariwebscraper
Author: John/Jane Doe
Author-email: j.doe@example.com
License: MIT
Classifier: Programming Language :: Python :: 3
Classifier: License :: OSI Approved :: MIT License
Classifier: Operating System :: OS Independent
Requires-Python: >=3.6
License-File: LICENSE
Requires-Dist: beautifulsoup4==4.9.3
Requires-Dist: requests==2.25.1
Dynamic: author
Dynamic: author-email
Dynamic: classifier
Dynamic: description
Dynamic: description-content-type
Dynamic: home-page
Dynamic: license
Dynamic: requires-dist
Dynamic: requires-python
Dynamic: summary
